temlogger/__init__.py
temlogger/formatter.py
temlogger/helpers.py
temlogger/temlogger.py
temlogger/tests.py
temlogger/providers/__init__.py
temlogger/providers/base.py
temlogger/providers/default.py
temlogger/providers/logstash.py
temlogger/providers/stackdriver.py
temlogger/tests/__init__.py
temlogger/tests/base.py
temlogger/tests/test_formatters.py
temlogger/tests/test_get_loggers.py
temlogger/tests/test_helpers.py
temlogger/tests/test_setup_event_handlers.py
temlogger_test-0.1.0b0.dist-info/DESCRIPTION.rst
temlogger_test-0.1.0b0.dist-info/METADATA
temlogger_test-0.1.0b0.dist-info/RECORD
temlogger_test-0.1.0b0.dist-info/WHEEL
temlogger_test-0.1.0b0.dist-info/metadata.json
temlogger_test-0.1.0b0.dist-info/top_level.txt
